uv_import_constraint_dependencies/__init__.py
uv_import_constraint_dependencies/__main__.py
uv_import_constraint_dependencies/cli.py
uv_import_constraint_dependencies/parser.py
uv_import_constraint_dependencies/toml_handler.py
uv_import_constraint_dependencies/uri_handler.py
uv_import_constraint_dependencies-0.1.2.dist-info/METADATA
uv_import_constraint_dependencies-0.1.2.dist-info/WHEEL
uv_import_constraint_dependencies-0.1.2.dist-info/entry_points.txt
uv_import_constraint_dependencies-0.1.2.dist-info/licenses/LICENSE
uv_import_constraint_dependencies-0.1.2.dist-info/RECORD
