Metadata-Version: 2.4
Name: uv-import-constraint-dependencies
Version: 0.1.2
Summary: Import constraints.txt into pyproject.toml as tool.uv.constraint-dependencies
Project-URL: Homepage, https://github.com/MrTango/uv-import-constraint-dependencies
Project-URL: Repository, https://github.com/MrTango/uv-import-constraint-dependencies
Author-email: Maik Dertappen <md@derico.de>
License-Expression: MIT
License-File: LICENSE
Keywords: cli,constraints,pyproject,uv
Classifier: Development Status :: 4 - Beta
Classifier: Environment :: Console
Classifier: Intended Audience :: Developers
Classifier: License :: OSI Approved :: MIT License
Classifier: Operating System :: OS Independent
Classifier: Programming Language :: Python :: 3
Classifier: Programming Language :: Python :: 3.10
Classifier: Programming Language :: Python :: 3.11
Classifier: Programming Language :: Python :: 3.12
Classifier: Topic :: Software Development :: Build Tools
Requires-Python: >=3.10
Requires-Dist: click>=8.0
Requires-Dist: tomlkit>=0.12
Provides-Extra: dev
Requires-Dist: pytest-cov; extra == 'dev'
Requires-Dist: pytest>=7.0; extra == 'dev'
